crecs/__init__.py
crecs/ds/__init__.py
crecs/ds/abc.py
crecs/ds/common.py
crecs/ds/dataset.py
crecs/ds/dense.py
crecs/ds/matrix.py
crecs/ds/sparse.py
crecs/ds/utils.py
crecs/ds/visitor.py
crecs/ev.py
crecs/rs/__init__.py
crecs/rs/abc.py
crecs/rs/base.py
crecs/rs/knn.py
crecs/rs/random.py
crecs/rs/toppop.py
crecs/rs/utils.py
crecs/sage/__init__.py
crecs/sage/abc.py
crecs/sage/app.py
crecs/sage/base.py
crecs/sage/train.py
crecs/sage/utils.py
crecs/utils.py
crecs-2019.9.0.dist-info/WHEEL
crecs-2019.9.0.dist-info/METADATA
crecs-2019.9.0.dist-info/RECORD
