Metadata-Version: 2.1
Name: crecs
Version: 2019.9.0
Summary: 
Author: Germano Gabbianelli
Author-email: git@germano.dev
Requires-Python: >=3.6
Classifier: Programming Language :: Python :: 3
Classifier: Programming Language :: Python :: 3.6
Classifier: Programming Language :: Python :: 3.7
Provides-Extra: container
Provides-Extra: sagemaker
Requires-Dist: numpy (>=1.17)
Requires-Dist: sagemaker (>=1.18,<2.0); extra == "sagemaker"
Requires-Dist: sagemaker-containers (>=2.4,<3.0); extra == "container"
Requires-Dist: scikit-learn (>=0.19.1)
Requires-Dist: scipy (>=0.16)
Requires-Dist: typing_extensions (>=3.7,<4.0)
